EverythingCurl/README.md
EverythingCurl/__init__.py
EverythingCurl/__main__.py
EverythingCurl/file.epub
EverythingCurl/index.html
EverythingCurl/css/__init__.py
EverythingCurl/css/annotations.css
EverythingCurl/css/main.css
EverythingCurl/css/normalize.css
EverythingCurl/css/popup.css
EverythingCurl/font/__init__.py
EverythingCurl/font/fontello.eot
EverythingCurl/font/fontello.svg
EverythingCurl/font/fontello.ttf
EverythingCurl/font/fontello.woff
EverythingCurl/img/__init__.py
EverythingCurl/img/annotator-glyph-sprite.png
EverythingCurl/img/annotator-icon-sprite.png
EverythingCurl/img/apple-touch-icon.png
EverythingCurl/img/cancelfullscreen.png
EverythingCurl/img/close.png
EverythingCurl/img/fullscreen.png
EverythingCurl/img/loader.gif
EverythingCurl/img/menu-icon.png
EverythingCurl/img/save.png
EverythingCurl/img/saved.png
EverythingCurl/img/settings-s.png
EverythingCurl/img/settings.png
EverythingCurl/img/star.png
EverythingCurl/js/__init__.py
EverythingCurl/js/epub.js
EverythingCurl/js/epub.min.js
EverythingCurl/js/epub.min.map
EverythingCurl/js/hooks.min.js
EverythingCurl/js/hooks.min.map
EverythingCurl/js/reader.js
EverythingCurl/js/reader.js.map
EverythingCurl/js/reader.min.js
EverythingCurl/js/reader.min.map
EverythingCurl/js/hooks/__init__.py
EverythingCurl/js/hooks/extensions/__init__.py
EverythingCurl/js/hooks/extensions/highlight.js
EverythingCurl/js/libs/__init__.py
EverythingCurl/js/libs/jquery.min.js
EverythingCurl/js/libs/localforage.min.js
EverythingCurl/js/libs/screenfull.js
EverythingCurl/js/libs/screenfull.min.js
EverythingCurl/js/libs/zip.min.js
EverythingCurl/js/plugins/__init__.py
EverythingCurl/js/plugins/hypothesis.js
EverythingCurl/js/plugins/search.js
everything_curl-2024.3.3.0.dist-info/METADATA
everything_curl-2024.3.3.0.dist-info/WHEEL
everything_curl-2024.3.3.0.dist-info/entry_points.txt
everything_curl-2024.3.3.0.dist-info/top_level.txt
everything_curl-2024.3.3.0.dist-info/RECORD
